nanocontroller/__init__.py
nanocontroller/api.py
nanocontroller/nano.py
nanocontroller/helpers/__init__.py
nanocontroller/helpers/auth_generate.py
nanocontroller/helpers/colors.py
nanocontroller/helpers/openmeteo.py
nanocontroller/helpers/weather_codes.py
nanocontroller-1.0.3.dist-info/LICENSE
nanocontroller-1.0.3.dist-info/METADATA
nanocontroller-1.0.3.dist-info/WHEEL
nanocontroller-1.0.3.dist-info/top_level.txt
nanocontroller-1.0.3.dist-info/RECORD
