Metadata-Version: 2.1
Name: nanocontroller
Version: 1.0.3
Summary: NanoLeaf controller
Author-email: Jared Gantt <jaredgantt@gmail.com>
License: MIT
Project-URL: Homepage, https://github.com/JJGantt/nano_control
Keywords: nanoleaf
Requires-Python: >=3.6
License-File: LICENSE
Requires-Dist: openmeteo_requests==1.3.0
Requires-Dist: numpy==2.1.3
Requires-Dist: openmeteo_sdk==1.18.0
Requires-Dist: pandas==2.2.3
Requires-Dist: python-dotenv==1.0.1
Requires-Dist: httpx==0.27.2
Requires-Dist: requests==2.32.3
Requires-Dist: retry-requests==2.0.0
Requires-Dist: requests-cache==1.2.1
